windows_metadata/__init__.py
windows_metadata/windows_metadata.py
windows_metadata-0.1.2.dist-info/LICENSE
windows_metadata-0.1.2.dist-info/METADATA
windows_metadata-0.1.2.dist-info/WHEEL
windows_metadata-0.1.2.dist-info/top_level.txt
windows_metadata-0.1.2.dist-info/RECORD
