Metadata-Version: 2.1
Name: windows-metadata
Version: 0.1.2
Summary: Read Windows metadata from files
Author-email: Sébastien Paine <sebastienpaine@me.com>
License: MIT License
Project-URL: Homepage, https://github.com/sebastienpaine/windows_metadata
Project-URL: Bug Tracker, https://github.com/sebastienpaine/windows_metadata/issues
Keywords: windows,metadata,attributes,details
Classifier: Programming Language :: Python :: 3
Classifier: License :: OSI Approved :: MIT License
Classifier: Operating System :: Microsoft :: Windows
Requires-Python: >=3.6
Provides-Extra: dev
License-File: LICENSE
